pyattribution/AttributionTools.py
pyattribution/DAO.py
pyattribution/PortfolioTools.py
pyattribution/TSCollector.py
pyattribution/__init__.py
pyattribution/configs.py
pyattribution-0.1.1.dist-info/METADATA
pyattribution-0.1.1.dist-info/WHEEL
pyattribution-0.1.1.dist-info/top_level.txt
pyattribution-0.1.1.dist-info/RECORD
